swent/__init__.py
swent/cli.py
swent/config.py
swent/core.py
swent/entropy_calculator.py
swent/metrics.py
swent/py.typed
swent/reports.py
swent/analyzers/__init__.py
swent/analyzers/base.py
swent/analyzers/complexity.py
swent/analyzers/dependencies.py
swent/analyzers/documentation.py
swent/analyzers/duplication.py
swent/analyzers/git_history.py
swent/analyzers/maintainability.py
swent/analyzers/size.py
swent-0.1.0.dist-info/licenses/AUTHORS.md
swent-0.1.0.dist-info/licenses/LICENSE
swent-0.1.0.dist-info/METADATA
swent-0.1.0.dist-info/WHEEL
swent-0.1.0.dist-info/entry_points.txt
swent-0.1.0.dist-info/top_level.txt
swent-0.1.0.dist-info/RECORD
