Metadata-Version: 2.4
Name: swent
Version: 0.1.0
Summary: Software entropy measurement tool for Python projects
Author-email: Chad Hanna <crh184@psu.edu>
Maintainer-email: Chad Hanna <crh184@psu.edu>
License: MIT
Project-URL: Homepage, https://github.com/chadhanna/swent
Project-URL: Documentation, https://swent.readthedocs.io
Project-URL: Source Code, https://github.com/chadhanna/swent
Project-URL: Bug Tracker, https://github.com/chadhanna/swent/issues
Project-URL: Changelog, https://github.com/chadhanna/swent/blob/main/CHANGELOG.md
Keywords: software-entropy,code-quality,metrics,cyclomatic-complexity,maintainability,technical-debt,code-analysis,static-analysis,linting,duplication-detection
Classifier: Development Status :: 4 - Beta
Classifier: Intended Audience :: Developers
Classifier: License :: OSI Approved :: MIT License
Classifier: Operating System :: OS Independent
Classifier: Programming Language :: Python :: 3
Classifier: Programming Language :: Python :: 3.8
Classifier: Programming Language :: Python :: 3.9
Classifier: Programming Language :: Python :: 3.10
Classifier: Programming Language :: Python :: 3.11
Classifier: Programming Language :: Python :: 3.12
Classifier: Topic :: Software Development :: Quality Assurance
Classifier: Topic :: Software Development :: Testing
Classifier: Topic :: Software Development :: Libraries :: Python Modules
Classifier: Environment :: Console
Classifier: Natural Language :: English
Classifier: Typing :: Typed
Requires-Python: >=3.8
License-File: LICENSE
License-File: AUTHORS.md
Requires-Dist: click>=8.0
Requires-Dist: gitpython>=3.1
Requires-Dist: radon>=5.1
Requires-Dist: pycodestyle>=2.8
Requires-Dist: pydocstyle>=6.1
Requires-Dist: astroid>=2.12
Requires-Dist: pyyaml>=6.0
Requires-Dist: rich>=12.0
Requires-Dist: toml>=0.10
Provides-Extra: dev
Requires-Dist: pytest>=7.0; extra == "dev"
Requires-Dist: pytest-cov>=4.0; extra == "dev"
Requires-Dist: black>=22.0; extra == "dev"
Requires-Dist: isort>=5.10; extra == "dev"
Requires-Dist: mypy>=0.990; extra == "dev"
Requires-Dist: pre-commit>=2.20; extra == "dev"
Dynamic: license-file
